ukkomotif/__init__.py
ukkomotif/main.py
ukkomotif/parser.py
ukkomotif/ukkonen.py
ukkomotif/weeder.py
ukkomotif/cli/__init__.py
ukkomotif/cli/main.py
ukkomotif-1.0.dist-info/LICENSE
ukkomotif-1.0.dist-info/METADATA
ukkomotif-1.0.dist-info/WHEEL
ukkomotif-1.0.dist-info/entry_points.txt
ukkomotif-1.0.dist-info/top_level.txt
ukkomotif-1.0.dist-info/RECORD
